solana/__init__.py
solana/_layouts/__init__.py
solana/_layouts/vote_instructions.py
solana/constants.py
solana/exceptions.py
solana/py.typed
solana/rpc/__init__.py
solana/rpc/api.py
solana/rpc/async_api.py
solana/rpc/commitment.py
solana/rpc/core.py
solana/rpc/providers/__init__.py
solana/rpc/providers/async_base.py
solana/rpc/providers/async_http.py
solana/rpc/providers/base.py
solana/rpc/providers/core.py
solana/rpc/providers/http.py
solana/rpc/types.py
solana/rpc/websocket_api.py
solana/utils/__init__.py
solana/utils/cluster.py
solana/utils/security_txt.py
solana/utils/validate.py
solana/vote_program.py
spl/__init__.py
spl/memo/__init__.py
spl/memo/constants.py
spl/memo/instructions.py
spl/py.typed
spl/token/__init__.py
spl/token/_layouts.py
spl/token/async_client.py
spl/token/client.py
spl/token/constants.py
spl/token/core.py
spl/token/instructions.py
solana-0.37.0.dist-info/LICENSE
solana-0.37.0.dist-info/METADATA
solana-0.37.0.dist-info/WHEEL
solana-0.37.0.dist-info/RECORD
