Metadata-Version: 2.1
Name: solana
Version: 0.37.0
Summary: Solana Python API
Home-page: https://github.com/michaelhly/solanapy
License: MIT
Keywords: solana,blockchain,web3
Author: Michael Huang
Author-email: michaelhly@gmail.com
Requires-Python: >=3.9,<4.0
Classifier: Intended Audience :: Developers
Classifier: License :: OSI Approved :: MIT License
Classifier: Natural Language :: English
Classifier: Programming Language :: Python :: 3
Classifier: Programming Language :: Python :: 3.9
Classifier: Programming Language :: Python :: 3.10
Classifier: Programming Language :: Python :: 3.11
Classifier: Programming Language :: Python :: 3.12
Classifier: Programming Language :: Python :: 3.13
Requires-Dist: construct-typing (>=0.5.2,<0.6.0)
Requires-Dist: httpx (>=0.23.0)
Requires-Dist: solders (>=0.23.0,<0.24.0)
Requires-Dist: typing-extensions (>=4.2.0)
Requires-Dist: websockets (>=9.0,<=12.0)
Project-URL: Documentation, https://michaelhly.github.io/solana-py/
